LICENSE
MANIFEST.in
README.md
VERSION_NUMBER
setup.cfg
setup.py
onnx_caffe2/__init__.py
onnx_caffe2/backend.py
onnx_caffe2/backend_rep.py
onnx_caffe2/error.py
onnx_caffe2/frontend.py
onnx_caffe2/helper.py
onnx_caffe2/workspace.py
onnx_caffe2.egg-info/PKG-INFO
onnx_caffe2.egg-info/SOURCES.txt
onnx_caffe2.egg-info/dependency_links.txt
onnx_caffe2.egg-info/entry_points.txt
onnx_caffe2.egg-info/requires.txt
onnx_caffe2.egg-info/top_level.txt
onnx_caffe2/bin/__init__.py
onnx_caffe2/bin/conversion.py
tests/__init__.py
tests/caffe2_ref_test.py
tests/conversion_test.py
tests/helper_test.py
tests/onnx_backend_test.py
tests/ssa_test.py
tests/test_utils.py