Metadata-Version: 1.0
Name: onnx-caffe2
Version: 1.0.0
Summary: Caffe2 frontend and backend of Open Neural Network Exchange
Home-page: https://github.com/onnx/onnx-caffe2
Author: bddppq
Author-email: jbai@fb.com
License: UNKNOWN
Platform: UNKNOWN
